Metadata-Version: 2.1
Name: morbius
Version: 0.0.1
Summary: simple example of packagin code
Home-page: https://github.com
Author: xariusrke
Author-email: b3f0cus@icloud.com
License: MIT
Classifier: License :: OSI Approved :: MIT License
Classifier: Programming Language :: Python :: 3
Classifier: Programming Language :: Python :: 3.7
